<?xml version="1.0" encoding="UTF-8" standalone="no"?>
<window xmlns="http://jmix.io/schema/ui/window"
        caption="msg://boxLayoutScreen.caption">
    <!-- tag::layout-start[] -->
    <layout>
    <!-- end::layout-start[] -->

        <!-- tag::hbox[] -->
        <hbox id="hbox"
              spacing="true">
            <label align="MIDDLE_LEFT"
                   value="Label"/>
            <textField inputPrompt="TextField" required="true"/>
            <button caption="Button"/>
            <button caption="Button"/>
        </hbox>
        <!-- end::hbox[] -->

        <!-- tag::vbox[] -->
        <vbox id="vbox"
              spacing="true">
            <label value="Label"/>
            <textField inputPrompt="TextField" required="true"/>
            <button caption="Button"/>
            <button caption="Button"/>
        </vbox>
        <!-- end::vbox[] -->

        <!-- tag::flow-box[] -->
        <flowBox id="flowBox"
                 spacing="true"
                 width="300px">
            <label value="Label"/>
            <textField inputPrompt="TextField"/>
            <button caption="Button"/>
            <button caption="Button"/>
        </flowBox>
        <!-- end::flow-box[] -->

        <!-- tag::vaadin[] -->
        <vbox stylename="well"
              height="200px"
              width="300px"
              expand="message"
              spacing="true">
            <hbox stylename="v-panel-caption"
                  width="100%">
                <label value="Widget caption"/>
                <button align="MIDDLE_RIGHT"
                        icon="font-icon:EXPAND"
                        stylename="borderless-colored"/>
            </hbox>
            <textArea id="message"
                      inputPrompt="Enter your message here..."
                      width="280"
                      align="MIDDLE_CENTER"/>
            <button caption="Send message"
                    width="100%"/>
        </vbox>
        <!-- end::vaadin[] -->

        <!-- tag::layout-end[] -->
    </layout>
    <!-- end::layout-end[] -->
</window>